newmm_tokenizer/__init__.py
newmm_tokenizer/common.py
newmm_tokenizer/corpus.py
newmm_tokenizer/newmm.py
newmm_tokenizer/tcc.py
newmm_tokenizer/tokenizer.py
newmm_tokenizer/trie.py
newmm_tokenizer/words_th.txt
newmm_tokenizer-0.2.2.dist-info/METADATA
newmm_tokenizer-0.2.2.dist-info/WHEEL
newmm_tokenizer-0.2.2.dist-info/top_level.txt
newmm_tokenizer-0.2.2.dist-info/RECORD
