Metadata-Version: 2.1
Name: newmm-tokenizer
Version: 0.2.2
Summary: Standalone Dictionary-based, Maximum Matching + Thai Character Cluster (newmm) tokenizer extracted from PyThaiNLP
Home-page: https://github.com/wisesight/newmm-tokenizer
Author: WISESIGHT Product Development
Author-email: tequila@wisesight.com
License: UNKNOWN
Platform: UNKNOWN
Classifier: Programming Language :: Python :: 3
Classifier: License :: OSI Approved :: Apache Software License
Classifier: Natural Language :: Thai
Classifier: Topic :: Scientific/Engineering :: Artificial Intelligence
Classifier: Topic :: Text Processing
Classifier: Topic :: Text Processing :: General
Classifier: Topic :: Text Processing :: Linguistic
Requires-Python: >=3.7
